README.rst
setup.py
django_prototype.egg-info/PKG-INFO
django_prototype.egg-info/SOURCES.txt
django_prototype.egg-info/dependency_links.txt
django_prototype.egg-info/requires.txt
django_prototype.egg-info/top_level.txt
prototype/__init__.py
prototype/models.py
prototype/runtests.py
prototype/settings.py
prototype/tests.py
prototype/urls.py
prototype/views.py