Metadata-Version: 1.0
Name: django-prototype
Version: 0.2
Summary: Simple application to build interactive HTML based on the Django templating system.
Home-page: http://github.com/goodtune/django-prototype
Author: Gary Reynolds
Author-email: gary@touch.asn.au
License: UNKNOWN
Platform: UNKNOWN
